croning/__init__.py
croning/exceptions.py
croning/schedule.py
croning/scheduler.py
croning/singleton.py
croning-0.1.1.dist-info/METADATA
croning-0.1.1.dist-info/WHEEL
croning-0.1.1.dist-info/licenses/LICENSE
croning-0.1.1.dist-info/RECORD
