Metadata-Version: 2.3
Name: croning
Version: 0.1.1
Summary: Cron-style scheduling library.
Project-URL: Repository, https://github.com/isuckatlinux/croning
Author-email: Pedro García <pedroluisgarciamontil@gmail.com>
Maintainer-email: Pedro García <pedroluisgarciamontil@gmail.com>
License: MIT License
License-File: LICENSE
Keywords: cron,crontab,python,scheduler
Classifier: Development Status :: 4 - Beta
Classifier: Programming Language :: Python
Requires-Python: >=3.8
Requires-Dist: croniter==2.0.5
